{
    "@class": "com.kony.gen.viz.model.component.KVizButton",
    "DNDConfig": null,
    "_margin_": [
        6,
        6,
        6,
        6
    ],
    "_padding_": [
        4,
        4,
        4,
        4
    ],
    "_skin_": "sb0cd719d9964f0ab1bb048e5d9c6354",
    "_text_": "Check In",
    "canUpdateUI": true,
    "containerWeight": 100,
    "containerweight": 100,
    "contentAlignment": 5,
    "contentalignment": 5,
    "displayText": true,
    "displaytext": true,
    "enabled": false,
    "focusSkin": "sd7efb5a1e634dd0b34998c573f9af47",
    "focusskin": "sd7efb5a1e634dd0b34998c573f9af47",
    "id": "Button0ec86f5c837b540",
    "info": null,
    "isVisible": true,
    "isvisible": true,
    "kuid": "eacb148ae7b648679268416a79069123",
    "margin": [
        6,
        6,
        6,
        6
    ],
    "name": "kony.ui.Button",
    "onClick": "AS_Button_20fdc119b68c4ced9a369652428c3c8a",
    "onclick": "AS_Button_20fdc119b68c4ced9a369652428c3c8a",
    "padding": [
        4,
        4,
        4,
        4
    ],
    "parent": "frmDummy",
    "pf": "frmDummy",
    "render": true,
    "skin": "sb0cd719d9964f0ab1bb048e5d9c6354",
    "text": "Check In",
    "wType": "Button",
    "widgetAlignment": 5
}