{
    "@class": "com.kony.gen.viz.model.component.KVizLabel",
    "DNDConfig": null,
    "_margin_": [
        0,
        1,
        0,
        1
    ],
    "_padding_": [
        0,
        0,
        0,
        0
    ],
    "_skin_": "sb5a568a59c147cc9f05ba629f86f839",
    "_text_": "Label",
    "_wrapping_": 2,
    "canUpdateUI": true,
    "containerId": true,
    "containerWeight": 26,
    "containerweight": 26,
    "contentAlignment": 4,
    "contentalignment": 4,
    "enabled": false,
    "id": "lblAM",
    "info": null,
    "ipad": {
        "psp": {
            "wrapping": 2
        }
    },
    "iphone": {
        "psp": {
            "wrapping": 2
        }
    },
    "isVisible": true,
    "isvisible": true,
    "kuid": "03bdd6c426454d228e494558b4695a71",
    "margin": [
        0,
        1,
        0,
        1
    ],
    "marginInPixel": false,
    "margininpixel": false,
    "name": "kony.ui.Label",
    "paddInPixel": [
        0,
        0,
        0,
        0
    ],
    "padding": [
        0,
        0,
        0,
        0
    ],
    "parent": "CopyHBox0cdf6f5628c4243",
    "pf": "CopyVBox0b3c7e0aae7a740",
    "render": true,
    "skin": "sb5a568a59c147cc9f05ba629f86f839",
    "text": "Label",
    "toolTip": "",
    "tooltip": "",
    "wType": "Label",
    "widgetAlignment": 4,
    "widgetalignment": 4,
    "wrapping": 2
}