{
    "@class": "com.kony.gen.viz.model.component.KVizLabel",
    "DNDConfig": null,
    "_margin_": [
        28,
        1,
        1,
        1
    ],
    "_padding_": [
        0,
        0,
        0,
        0
    ],
    "_skin_": "s137d4bdd94a474182b559f95ea504bd",
    "_text_": "Label",
    "_wrapping_": 2,
    "canUpdateUI": true,
    "containerId": true,
    "containerWeight": 100,
    "containerweight": 100,
    "contentAlignment": 4,
    "contentalignment": 4,
    "enabled": false,
    "id": "lblDeparted",
    "info": null,
    "ipad": {
        "psp": {
            "wrapping": 2
        }
    },
    "iphone": {
        "psp": {
            "wrapping": 2
        }
    },
    "isSegmentChild": true,
    "isVisible": true,
    "isvisible": true,
    "kuid": "fa8589f7b7414f34b5861cc2fce04fb7",
    "margin": [
        28,
        1,
        1,
        1
    ],
    "marginInPixel": false,
    "margininpixel": false,
    "name": "kony.ui.Label",
    "paddInPixel": [
        0,
        0,
        0,
        0
    ],
    "padding": [
        0,
        0,
        0,
        0
    ],
    "parent": "CopyHBox073c3a18d071441",
    "pf": "VBox00cd629edf6104d",
    "render": true,
    "skin": "s137d4bdd94a474182b559f95ea504bd",
    "text": "Label",
    "toolTip": "",
    "tooltip": "",
    "wType": "Label",
    "widgetAlignment": 5,
    "wrapping": 2
}